hammuon/__init__.py
hammuon/data_structure/bubble_sort.py
hammuon/data_structure/quick_sort.py
hammuon/data_structure/selection_sort.py
hammuon/metrics/euclidean_distance.py
hammuon/metrics/mahalanobis_distance.py
hammuon-0.1.11.dist-info/WHEEL
hammuon-0.1.11.dist-info/METADATA
hammuon-0.1.11.dist-info/RECORD
